{"Modules": [{"Module": "M14", "Boundary": [["218.4", "651.2"], ["218.4", "714.8"], ["218.3", "714.8"], ["218.3", "730.2"], ["30.0", "730.2"], ["30.0", "651.2"]], "Module_type": "GATE", "Ports": [{"Location": [["30.0", "664.2"], ["34.7", "664.2"], ["34.7", "717.2"], ["30.0", "717.2"]], "Type": "SD"}, {"Location": [["218.4", "651.2"], ["218.4", "714.8"], ["218.3", "714.8"], ["218.3", "730.2"], ["36.9", "730.2"], ["36.9", "651.2"]], "Type": "GATE"}, {"Location": [["207.8", "657.0"], ["213.6", "657.0"], ["213.6", "709.0"], ["207.8", "709.0"]], "Type": "SD"}]}, {"Ports": [{"Location": [["157.7", "109.6"], ["219.9", "109.6"], ["219.9", "113.9"], ["157.7", "113.9"]], "Type": "SD"}, {"Location": [["145.3", "10.0"], ["232.3", "10.0"], ["232.3", "107.9"], ["145.3", "107.9"]], "Type": "GATE"}, {"Location": [["151.1", "14.8"], ["226.5", "14.8"], ["226.5", "20.4"], ["151.1", "20.4"]], "Type": "SD"}], "Module": "M9", "Boundary": [["145.3", "10.0"], ["232.3", "10.0"], ["232.3", "113.9"], ["145.3", "113.9"]], "Module_type": "GATE"}, {"Ports": [{"Location": [["34.1", "362.8"], ["76.8", "362.8"], ["76.8", "368.1"], ["34.1", "368.1"]], "Type": "SD"}, {"Location": [["20.0", "245.2"], ["90.9", "245.2"], ["90.9", "361.0"], ["20.0", "361.0"]], "Type": "GATE"}, {"Location": [["25.6", "249.8"], ["85.3", "249.8"], ["85.3", "256.0"], ["25.6", "256.0"]], "Type": "SD"}], "Module": "M5", "Boundary": [["20.0", "245.2"], ["90.9", "245.2"], ["90.9", "368.1"], ["20.0", "368.1"]], "Module_type": "GATE"}, {"Ports": [{"Location": [["10.0", "782.9"], ["16.0", "782.9"], ["16.0", "820.5"], ["10.0", "820.5"]], "Type": "SD"}, {"Location": [["215.0", "770.2"], ["215.0", "817.6"], ["214.7", "817.6"], ["214.7", "833.2"], ["17.1", "833.2"], ["17.1", "770.2"]], "Type": "GATE"}, {"Location": [["204.8", "775.3"], ["210.9", "775.3"], ["210.9", "812.5"], ["204.8", "812.5"]], "Type": "SD"}], "Module": "M11", "Boundary": [["215.0", "770.2"], ["215.0", "817.6"], ["214.7", "817.6"], ["214.7", "833.2"], ["10.0", "833.2"], ["10.0", "770.2"]], "Module_type": "GATE"}, {"Ports": [{"Location": [["153.9", "579.2"], ["238.3", "579.2"], ["238.3", "583.3"], ["153.9", "583.3"]], "Type": "SD"}, {"Location": [["140.9", "387.4"], ["251.3", "387.4"], ["251.3", "578.0"], ["140.9", "578.0"]], "Type": "GATE"}, {"Location": [["147.4", "392.9"], ["244.8", "392.9"], ["244.8", "398.3"], ["147.4", "398.3"]], "Type": "SD"}], "Module": "M1", "Boundary": [["140.9", "387.4"], ["251.3", "387.4"], ["251.3", "583.3"], ["140.9", "583.3"]], "Module_type": "GATE"}, {"Ports": [{"Location": [["279.1", "286.0"], ["284.4", "286.0"], ["284.4", "317.9"], ["279.1", "317.9"]], "Type": "SD"}, {"Location": [["422.9", "274.1"], ["422.9", "316.9"], ["422.8", "316.9"], ["422.8", "329.8"], ["287.4", "329.8"], ["287.4", "274.1"]], "Type": "GATE"}, {"Location": [["412.7", "279.2"], ["418.8", "279.2"], ["418.8", "311.8"], ["412.7", "311.8"]], "Type": "SD"}], "Module": "M6", "Boundary": [["422.9", "274.1"], ["422.9", "316.9"], ["422.8", "316.9"], ["422.8", "329.8"], ["279.1", "329.8"], ["279.1", "274.1"]], "Module_type": "GATE"}, {"Ports": [{"Location": [["314.2", "495.7"], ["382.6", "495.7"], ["382.6", "500.3"], ["314.2", "500.3"]], "Type": "SD"}, {"Location": [["301.3", "359.8"], ["380.4", "359.8"], ["380.4", "360.0"], ["395.5", "360.0"], ["395.5", "492.9"], ["301.3", "492.9"]], "Type": "GATE"}, {"Location": [["307.3", "364.8"], ["374.4", "364.8"], ["374.4", "371.0"], ["307.3", "371.0"]], "Type": "SD"}], "Module": "M2", "Boundary": [["301.3", "359.8"], ["380.4", "359.8"], ["380.4", "360.0"], ["395.5", "360.0"], ["395.5", "500.3"], ["301.3", "500.3"]], "Module_type": "GATE"}, {"Ports": [{"Location": [["377.5", "249.7"], ["413.7", "249.7"], ["413.7", "254.1"], ["377.5", "254.1"]], "Type": "SD"}, {"Location": [["364.5", "135.4"], ["412.1", "135.4"], ["412.1", "135.4"], ["426.7", "135.4"], ["426.7", "248.7"], ["364.5", "248.7"]], "Type": "GATE"}, {"Location": [["370.9", "140.8"], ["405.7", "140.8"], ["405.7", "146.1"], ["370.9", "146.1"]], "Type": "SD"}], "Module": "M16", "Boundary": [["364.5", "135.4"], ["412.1", "135.4"], ["412.1", "135.4"], ["426.7", "135.4"], ["426.7", "254.1"], ["364.5", "254.1"]], "Module_type": "GATE"}, {"Ports": [{"Location": [["252.3", "23.9"], ["258.2", "23.9"], ["258.2", "101.5"], ["252.3", "101.5"]], "Type": "SD"}, {"Location": [["426.7", "10.0"], ["426.7", "97.7"], ["426.4", "97.7"], ["426.4", "115.4"], ["259.8", "115.4"], ["259.8", "10.0"]], "Type": "GATE"}, {"Location": [["416.2", "15.6"], ["422.1", "15.6"], ["422.1", "92.1"], ["416.2", "92.1"]], "Type": "SD"}], "Module": "M13", "Boundary": [["426.7", "10.0"], ["426.7", "97.7"], ["426.4", "97.7"], ["426.4", "115.4"], ["252.3", "115.4"], ["252.3", "10.0"]], "Module_type": "GATE"}, {"Ports": [{"Location": [["258.4", "656.7"], ["263.5", "656.7"], ["263.5", "691.0"], ["258.4", "691.0"]], "Type": "SD"}, {"Location": [["421.3", "643.6"], ["421.3", "690.0"], ["421.2", "690.0"], ["421.2", "704.1"], ["265.9", "704.1"], ["265.9", "643.6"]], "Type": "GATE"}, {"Location": [["410.1", "649.5"], ["416.4", "649.5"], ["416.4", "684.1"], ["410.1", "684.1"]], "Type": "SD"}], "Module": "M10", "Boundary": [["421.3", "643.6"], ["421.3", "690.0"], ["421.2", "690.0"], ["421.2", "704.1"], ["258.4", "704.1"], ["258.4", "643.6"]], "Module_type": "GATE"}, {"Ports": [{"Location": [["130.9", "280.0"], ["136.4", "280.0"], ["136.4", "325.5"], ["130.9", "325.5"]], "Type": "SD"}, {"Location": [["249.1", "268.1"], ["249.1", "337.4"], ["138.6", "337.4"], ["138.6", "268.1"]], "Type": "GATE"}, {"Location": [["239.0", "274.4"], ["243.8", "274.4"], ["243.8", "331.1"], ["239.0", "331.1"]], "Type": "SD"}], "Module": "M7", "Boundary": [["249.1", "268.1"], ["249.1", "337.4"], ["130.9", "337.4"], ["130.9", "268.1"]], "Module_type": "GATE"}, {"Ports": [{"Location": [["291.3", "542.7"], ["296.9", "542.7"], ["296.9", "611.2"], ["291.3", "611.2"]], "Type": "SD"}, {"Location": [["421.6", "530.3"], ["421.6", "608.1"], ["421.1", "608.1"], ["421.1", "623.6"], ["298.2", "623.6"], ["298.2", "530.3"]], "Type": "GATE"}, {"Location": [["412.1", "536.1"], ["416.8", "536.1"], ["416.8", "602.3"], ["412.1", "602.3"]], "Type": "SD"}], "Module": "M3", "Boundary": [["421.6", "530.3"], ["421.6", "608.1"], ["421.1", "608.1"], ["421.1", "623.6"], ["291.3", "623.6"], ["291.3", "530.3"]], "Module_type": "GATE"}, {"Ports": [{"Location": [["24.3", "605.6"], ["81.8", "605.6"], ["81.8", "611.2"], ["24.3", "611.2"]], "Type": "SD"}, {"Location": [["10.0", "398.1"], ["79.3", "398.1"], ["79.3", "398.4"], ["96.1", "398.4"], ["96.1", "603.7"], ["10.0", "603.7"]], "Type": "GATE"}, {"Location": [["16.6", "403.7"], ["72.7", "403.7"], ["72.7", "409.2"], ["16.6", "409.2"]], "Type": "SD"}], "Module": "M15", "Boundary": [["10.0", "398.1"], ["79.3", "398.1"], ["79.3", "398.4"], ["96.1", "398.4"], ["96.1", "611.2"], ["10.0", "611.2"]], "Module_type": "GATE"}, {"Ports": [{"Location": [["23.4", "209.2"], ["111.9", "209.2"], ["111.9", "215.2"], ["23.4", "215.2"]], "Type": "SD"}, {"Location": [["10.0", "10.0"], ["109.1", "10.0"], ["109.1", "10.0"], ["125.3", "10.0"], ["125.3", "208.0"], ["10.0", "208.0"]], "Type": "GATE"}, {"Location": [["16.6", "15.6"], ["102.5", "15.6"], ["102.5", "20.9"], ["16.6", "20.9"]], "Type": "SD"}], "Module": "M12", "Boundary": [["10.0", "10.0"], ["109.1", "10.0"], ["109.1", "10.0"], ["125.3", "10.0"], ["125.3", "215.2"], ["10.0", "215.2"]], "Module_type": "GATE"}, {"Ports": [{"Location": [["268.4", "746.7"], ["274.4", "746.7"], ["274.4", "810.0"], ["268.4", "810.0"]], "Type": "SD"}, {"Location": [["411.2", "734.1"], ["411.2", "822.6"], ["275.8", "822.6"], ["275.8", "734.1"]], "Type": "GATE"}, {"Location": [["400.2", "739.9"], ["406.4", "739.9"], ["406.4", "816.8"], ["400.2", "816.8"]], "Type": "SD"}], "Module": "M8", "Boundary": [["411.2", "734.1"], ["411.2", "822.6"], ["268.4", "822.6"], ["268.4", "734.1"]], "Module_type": "GATE"}], "Area": [["-30.0", "-30.0"], ["466.7", "-30.0"], ["466.7", "873.2"], ["-30.0", "873.2"]], "Rules": ["GATE(5,5)", "SD(5,5)", "GATE_SD(0.5)", "GATE_ITO(0.5)", "SD_ITO(0.5)"]}