{"Modules": [{"Module": "M14", "Boundary": [["322.2", "317.9"], ["385.8", "317.9"], ["385.8", "508.5"], ["322.2", "508.5"]], "Module_type": "GATE", "Ports": [{"Location": [["334.5", "504.3"], ["373.5", "504.3"], ["373.5", "508.5"], ["334.5", "508.5"]], "Type": "SD"}, {"Location": [["322.2", "317.9"], ["385.8", "317.9"], ["385.8", "503.0"], ["322.2", "503.0"]], "Type": "GATE"}, {"Location": [["328.3", "323.0"], ["379.7", "323.0"], ["379.7", "327.6"], ["328.3", "327.6"]], "Type": "SD"}]}, {"Ports": [{"Location": [["148.8", "193.3"], ["201.5", "193.3"], ["201.5", "199.2"], ["148.8", "199.2"]], "Type": "SD"}, {"Location": [["135.1", "10.0"], ["200.0", "10.0"], ["200.0", "10.1"], ["215.2", "10.1"], ["215.2", "192.0"], ["135.1", "192.0"]], "Type": "GATE"}, {"Location": [["140.6", "14.5"], ["194.5", "14.5"], ["194.5", "21.9"], ["140.6", "21.9"]], "Type": "SD"}], "Module": "M9", "Boundary": [["135.1", "10.0"], ["200.0", "10.0"], ["200.0", "10.1"], ["215.2", "10.1"], ["215.2", "199.2"], ["135.1", "199.2"]], "Module_type": "GATE"}, {"Ports": [{"Location": [["32.8", "712.3"], ["123.3", "712.3"], ["123.3", "717.6"], ["32.8", "717.6"]], "Type": "SD"}, {"Location": [["20.0", "531.3"], ["136.1", "531.3"], ["136.1", "710.7"], ["20.0", "710.7"]], "Type": "GATE"}, {"Location": [["26.3", "536.6"], ["129.8", "536.6"], ["129.8", "541.8"], ["26.3", "541.8"]], "Type": "SD"}], "Module": "M5", "Boundary": [["20.0", "531.3"], ["136.1", "531.3"], ["136.1", "717.6"], ["20.0", "717.6"]], "Module_type": "GATE"}, {"Ports": [{"Location": [["301.3", "726.4"], ["386.7", "726.4"], ["386.7", "731.0"], ["301.3", "731.0"]], "Type": "SD"}, {"Location": [["286.1", "548.5"], ["386.1", "548.5"], ["386.1", "548.7"], ["401.9", "548.7"], ["401.9", "723.6"], ["286.1", "723.6"]], "Type": "GATE"}, {"Location": [["292.9", "554.3"], ["379.3", "554.3"], ["379.3", "561.4"], ["292.9", "561.4"]], "Type": "SD"}], "Module": "M11", "Boundary": [["286.1", "548.5"], ["386.1", "548.5"], ["386.1", "548.7"], ["401.9", "548.7"], ["401.9", "731.0"], ["286.1", "731.0"]], "Module_type": "GATE"}, {"Ports": [{"Location": [["255.2", "149.0"], ["260.0", "149.0"], ["260.0", "244.2"], ["255.2", "244.2"]], "Type": "SD"}, {"Location": [["388.1", "135.3"], ["388.1", "257.9"], ["262.1", "257.9"], ["262.1", "135.3"]], "Type": "GATE"}, {"Location": [["377.5", "140.9"], ["383.5", "140.9"], ["383.5", "252.3"], ["377.5", "252.3"]], "Type": "SD"}], "Module": "M1", "Boundary": [["388.1", "135.3"], ["388.1", "257.9"], ["255.2", "257.9"], ["255.2", "135.3"]], "Module_type": "GATE"}, {"Ports": [{"Location": [["24.2", "286.2"], ["76.0", "286.2"], ["76.0", "292.1"], ["24.2", "292.1"]], "Type": "SD"}, {"Location": [["10.0", "181.4"], ["90.2", "181.4"], ["90.2", "284.0"], ["10.0", "284.0"]], "Type": "GATE"}, {"Location": [["16.4", "186.8"], ["83.8", "186.8"], ["83.8", "193.7"], ["16.4", "193.7"]], "Type": "SD"}], "Module": "M6", "Boundary": [["10.0", "181.4"], ["90.2", "181.4"], ["90.2", "292.1"], ["10.0", "292.1"]], "Module_type": "GATE"}, {"Ports": [{"Location": [["245.2", "31.8"], ["249.4", "31.8"], ["249.4", "73.5"], ["245.2", "73.5"]], "Type": "SD"}, {"Location": [["381.4", "20.0"], ["381.4", "85.3"], ["250.9", "85.3"], ["250.9", "20.0"]], "Type": "GATE"}, {"Location": [["372.5", "25.3"], ["377.1", "25.3"], ["377.1", "80.0"], ["372.5", "80.0"]], "Type": "SD"}], "Module": "M2", "Boundary": [["381.4", "20.0"], ["381.4", "85.3"], ["245.2", "85.3"], ["245.2", "20.0"]], "Module_type": "GATE"}, {"Ports": [{"Location": [["228.5", "763.4"], ["232.7", "763.4"], ["232.7", "840.7"], ["228.5", "840.7"]], "Type": "SD"}, {"Location": [["364.7", "751.0"], ["364.7", "839.1"], ["364.6", "839.1"], ["364.6", "853.1"], ["234.8", "853.1"], ["234.8", "751.0"]], "Type": "GATE"}, {"Location": [["353.9", "756.9"], ["359.8", "756.9"], ["359.8", "833.2"], ["353.9", "833.2"]], "Type": "SD"}], "Module": "M16", "Boundary": [["364.7", "751.0"], ["364.7", "839.1"], ["364.6", "839.1"], ["364.6", "853.1"], ["228.5", "853.1"], ["228.5", "751.0"]], "Module_type": "GATE"}, {"Ports": [{"Location": [["191.3", "374.0"], ["266.2", "374.0"], ["266.2", "378.3"], ["191.3", "378.3"]], "Type": "SD"}, {"Location": [["175.3", "302.3"], ["282.2", "302.3"], ["282.2", "372.6"], ["175.3", "372.6"]], "Type": "GATE"}, {"Location": [["182.0", "308.0"], ["275.5", "308.0"], ["275.5", "315.0"], ["182.0", "315.0"]], "Type": "SD"}], "Module": "M13", "Boundary": [["175.3", "302.3"], ["282.2", "302.3"], ["282.2", "378.3"], ["175.3", "378.3"]], "Module_type": "GATE"}, {"Ports": [{"Location": [["100.1", "409.9"], ["142.6", "409.9"], ["142.6", "414.1"], ["100.1", "414.1"]], "Type": "SD"}, {"Location": [["87.4", "312.1"], ["138.0", "312.1"], ["138.0", "312.3"], ["155.3", "312.3"], ["155.3", "407.7"], ["87.4", "407.7"]], "Type": "GATE"}, {"Location": [["92.5", "316.2"], ["132.9", "316.2"], ["132.9", "322.0"], ["92.5", "322.0"]], "Type": "SD"}], "Module": "M10", "Boundary": [["87.4", "312.1"], ["138.0", "312.1"], ["138.0", "312.3"], ["155.3", "312.3"], ["155.3", "414.1"], ["87.4", "414.1"]], "Module_type": "GATE"}, {"Ports": [{"Location": [["33.8", "146.9"], ["91.3", "146.9"], ["91.3", "151.4"], ["33.8", "151.4"]], "Type": "SD"}, {"Location": [["20.0", "20.0"], ["105.1", "20.0"], ["105.1", "145.7"], ["20.0", "145.7"]], "Type": "GATE"}, {"Location": [["25.2", "24.2"], ["99.9", "24.2"], ["99.9", "30.9"], ["25.2", "30.9"]], "Type": "SD"}], "Module": "M7", "Boundary": [["20.0", "20.0"], ["105.1", "20.0"], ["105.1", "151.4"], ["20.0", "151.4"]], "Module_type": "GATE"}, {"Ports": [{"Location": [["191.6", "556.2"], ["249.8", "556.2"], ["249.8", "560.8"], ["191.6", "560.8"]], "Type": "SD"}, {"Location": [["175.3", "398.3"], ["248.7", "398.3"], ["248.7", "398.6"], ["266.1", "398.6"], ["266.1", "554.6"], ["175.3", "554.6"]], "Type": "GATE"}, {"Location": [["182.0", "404.0"], ["242.0", "404.0"], ["242.0", "411.2"], ["182.0", "411.2"]], "Type": "SD"}], "Module": "M3", "Boundary": [["175.3", "398.3"], ["248.7", "398.3"], ["248.7", "398.6"], ["266.1", "398.6"], ["266.1", "560.8"], ["175.3", "560.8"]], "Module_type": "GATE"}, {"Ports": [{"Location": [["110.2", "231.7"], ["114.9", "231.7"], ["114.9", "269.8"], ["110.2", "269.8"]], "Type": "SD"}, {"Location": [["190.5", "219.2"], ["190.5", "282.3"], ["117.8", "282.3"], ["117.8", "219.2"]], "Type": "GATE"}, {"Location": [["180.5", "225.0"], ["185.7", "225.0"], ["185.7", "276.5"], ["180.5", "276.5"]], "Type": "SD"}], "Module": "M15", "Boundary": [["190.5", "219.2"], ["190.5", "282.3"], ["110.2", "282.3"], ["110.2", "219.2"]], "Module_type": "GATE"}, {"Ports": [{"Location": [["22.7", "495.5"], ["54.7", "495.5"], ["54.7", "501.3"], ["22.7", "501.3"]], "Type": "SD"}, {"Location": [["10.0", "312.1"], ["67.4", "312.1"], ["67.4", "493.0"], ["10.0", "493.0"]], "Type": "GATE"}, {"Location": [["17.0", "318.1"], ["60.4", "318.1"], ["60.4", "323.2"], ["17.0", "323.2"]], "Type": "SD"}], "Module": "M12", "Boundary": [["10.0", "312.1"], ["67.4", "312.1"], ["67.4", "501.3"], ["10.0", "501.3"]], "Module_type": "GATE"}, {"Ports": [{"Location": [["20.0", "774.1"], ["25.1", "774.1"], ["25.1", "830.8"], ["20.0", "830.8"]], "Type": "SD"}, {"Location": [["198.5", "760.1"], ["198.5", "844.8"], ["27.3", "844.8"], ["27.3", "760.1"]], "Type": "GATE"}, {"Location": [["187.5", "766.2"], ["193.4", "766.2"], ["193.4", "838.7"], ["187.5", "838.7"]], "Type": "SD"}], "Module": "M8", "Boundary": [["198.5", "760.1"], ["198.5", "844.8"], ["20.0", "844.8"], ["20.0", "760.1"]], "Module_type": "GATE"}], "Area": [["-30.0", "-30.0"], ["441.9", "-30.0"], ["441.9", "893.1"], ["-30.0", "893.1"]], "Rules": ["GATE(5,5)", "SD(5,5)", "GATE_SD(0.5)", "GATE_ITO(0.5)", "SD_ITO(0.5)"]}