{"Modules": [{"Module": "M14", "Boundary": [["221.5", "30.0"], ["221.5", "125.4"], ["221.4", "125.4"], ["221.4", "141.2"], ["30.0", "141.2"], ["30.0", "30.0"]], "Module_type": "GATE", "Ports": [{"Location": [["30.0", "42.4"], ["34.3", "42.4"], ["34.3", "128.8"], ["30.0", "128.8"]], "Type": "SD"}, {"Location": [["221.5", "30.0"], ["221.5", "125.4"], ["221.4", "125.4"], ["221.4", "141.2"], ["36.7", "141.2"], ["36.7", "30.0"]], "Type": "GATE"}, {"Location": [["211.0", "35.3"], ["217.2", "35.3"], ["217.2", "120.1"], ["211.0", "120.1"]], "Type": "SD"}]}, {"Ports": [{"Location": [["25.1", "768.8"], ["107.0", "768.8"], ["107.0", "773.4"], ["25.1", "773.4"]], "Type": "SD"}, {"Location": [["10.0", "669.6"], ["122.1", "669.6"], ["122.1", "765.9"], ["10.0", "765.9"]], "Type": "GATE"}, {"Location": [["16.2", "674.8"], ["115.9", "674.8"], ["115.9", "681.3"], ["16.2", "681.3"]], "Type": "SD"}], "Module": "M9", "Boundary": [["10.0", "669.6"], ["122.1", "669.6"], ["122.1", "773.4"], ["10.0", "773.4"]], "Module_type": "GATE"}, {"Ports": [{"Location": [["20.0", "585.5"], ["24.5", "585.5"], ["24.5", "625.7"], ["20.0", "625.7"]], "Type": "SD"}, {"Location": [["124.6", "571.6"], ["124.6", "623.3"], ["124.4", "623.3"], ["124.4", "639.6"], ["27.1", "639.6"], ["27.1", "571.6"]], "Type": "GATE"}, {"Location": [["113.1", "577.8"], ["119.4", "577.8"], ["119.4", "617.1"], ["113.1", "617.1"]], "Type": "SD"}], "Module": "M5", "Boundary": [["124.6", "571.6"], ["124.6", "623.3"], ["124.4", "623.3"], ["124.4", "639.6"], ["20.0", "639.6"], ["20.0", "571.6"]], "Module_type": "GATE"}, {"Ports": [{"Location": [["22.3", "535.8"], ["113.6", "535.8"], ["113.6", "541.6"], ["22.3", "541.6"]], "Type": "SD"}, {"Location": [["10.0", "317.5"], ["109.2", "317.5"], ["109.2", "317.5"], ["125.9", "317.5"], ["125.9", "534.3"], ["10.0", "534.3"]], "Type": "GATE"}, {"Location": [["15.5", "322.0"], ["103.7", "322.0"], ["103.7", "327.0"], ["15.5", "327.0"]], "Type": "SD"}], "Module": "M11", "Boundary": [["10.0", "317.5"], ["109.2", "317.5"], ["109.2", "317.5"], ["125.9", "317.5"], ["125.9", "541.6"], ["10.0", "541.6"]], "Module_type": "GATE"}, {"Ports": [{"Location": [["30.0", "825.4"], ["35.3", "825.4"], ["35.3", "903.2"], ["30.0", "903.2"]], "Type": "SD"}, {"Location": [["221.4", "813.4"], ["221.4", "915.2"], ["37.3", "915.2"], ["37.3", "813.4"]], "Type": "GATE"}, {"Location": [["211.0", "819.4"], ["216.4", "819.4"], ["216.4", "909.2"], ["211.0", "909.2"]], "Type": "SD"}], "Module": "M1", "Boundary": [["221.4", "813.4"], ["221.4", "915.2"], ["30.0", "915.2"], ["30.0", "813.4"]], "Module_type": "GATE"}, {"Ports": [{"Location": [["307.3", "432.6"], ["329.2", "432.6"], ["329.2", "437.6"], ["307.3", "437.6"]], "Type": "SD"}, {"Location": [["294.3", "268.3"], ["327.1", "268.3"], ["327.1", "268.4"], ["342.2", "268.4"], ["342.2", "431.3"], ["294.3", "431.3"]], "Type": "GATE"}, {"Location": [["300.8", "273.8"], ["320.6", "273.8"], ["320.6", "278.9"], ["300.8", "278.9"]], "Type": "SD"}], "Module": "M6", "Boundary": [["294.3", "268.3"], ["327.1", "268.3"], ["327.1", "268.4"], ["342.2", "268.4"], ["342.2", "437.6"], ["294.3", "437.6"]], "Module_type": "GATE"}, {"Ports": [{"Location": [["155.9", "341.0"], ["160.2", "341.0"], ["160.2", "408.1"], ["155.9", "408.1"]], "Type": "SD"}, {"Location": [["264.3", "327.5"], ["264.3", "421.6"], ["162.6", "421.6"], ["162.6", "327.5"]], "Type": "GATE"}, {"Location": [["253.1", "333.5"], ["259.3", "333.5"], ["259.3", "415.6"], ["253.1", "415.6"]], "Type": "SD"}], "Module": "M2", "Boundary": [["264.3", "327.5"], ["264.3", "421.6"], ["155.9", "421.6"], ["155.9", "327.5"]], "Module_type": "GATE"}, {"Ports": [{"Location": [["250.8", "971.2"], ["256.6", "971.2"], ["256.6", "1045.5"], ["250.8", "1045.5"]], "Type": "SD"}, {"Location": [["344.1", "958.8"], ["344.1", "1057.9"], ["258.8", "1057.9"], ["258.8", "958.8"]], "Type": "GATE"}, {"Location": [["335.0", "964.1"], ["339.8", "964.1"], ["339.8", "1052.6"], ["335.0", "1052.6"]], "Type": "SD"}], "Module": "M16", "Boundary": [["344.1", "958.8"], ["344.1", "1057.9"], ["250.8", "1057.9"], ["250.8", "958.8"]], "Module_type": "GATE"}, {"Ports": [{"Location": [["154.6", "561.1"], ["159.5", "561.1"], ["159.5", "616.4"], ["154.6", "616.4"]], "Type": "SD"}, {"Location": [["327.0", "547.4"], ["327.0", "630.1"], ["161.1", "630.1"], ["161.1", "547.4"]], "Type": "GATE"}, {"Location": [["315.4", "552.7"], ["322.7", "552.7"], ["322.7", "624.8"], ["315.4", "624.8"]], "Type": "SD"}], "Module": "M13", "Boundary": [["327.0", "547.4"], ["327.0", "630.1"], ["154.6", "630.1"], ["154.6", "547.4"]], "Module_type": "GATE"}, {"Ports": [{"Location": [["154.6", "662.9"], ["160.1", "662.9"], ["160.1", "757.3"], ["154.6", "757.3"]], "Type": "SD"}, {"Location": [["298.9", "650.1"], ["298.9", "770.1"], ["162.6", "770.1"], ["162.6", "650.1"]], "Type": "GATE"}, {"Location": [["289.3", "655.7"], ["294.3", "655.7"], ["294.3", "764.5"], ["289.3", "764.5"]], "Type": "SD"}], "Module": "M10", "Boundary": [["298.9", "650.1"], ["298.9", "770.1"], ["154.6", "770.1"], ["154.6", "650.1"]], "Module_type": "GATE"}, {"Ports": [{"Location": [["283.7", "233.7"], ["321.7", "233.7"], ["321.7", "238.3"], ["283.7", "238.3"]], "Type": "SD"}, {"Location": [["271.5", "20.0"], ["333.9", "20.0"], ["333.9", "231.6"], ["271.5", "231.6"]], "Type": "GATE"}, {"Location": [["276.6", "24.1"], ["328.8", "24.1"], ["328.8", "29.6"], ["276.6", "29.6"]], "Type": "SD"}], "Module": "M7", "Boundary": [["271.5", "20.0"], ["333.9", "20.0"], ["333.9", "238.3"], ["271.5", "238.3"]], "Module_type": "GATE"}, {"Ports": [{"Location": [["124.7", "970.5"], ["130.6", "970.5"], ["130.6", "1044.6"], ["124.7", "1044.6"]], "Type": "SD"}, {"Location": [["230.8", "955.2"], ["230.8", "1059.9"], ["133.5", "1059.9"], ["133.5", "955.2"]], "Type": "GATE"}, {"Location": [["218.5", "960.8"], ["226.2", "960.8"], ["226.2", "1054.3"], ["218.5", "1054.3"]], "Type": "SD"}], "Module": "M3", "Boundary": [["230.8", "955.2"], ["230.8", "1059.9"], ["124.7", "1059.9"], ["124.7", "955.2"]], "Module_type": "GATE"}, {"Ports": [{"Location": [["10.0", "194.3"], ["14.5", "194.3"], ["14.5", "284.4"], ["10.0", "284.4"]], "Type": "SD"}, {"Location": [["224.5", "181.2"], ["224.5", "280.8"], ["223.9", "280.8"], ["223.9", "297.5"], ["15.6", "297.5"], ["15.6", "181.2"]], "Type": "GATE"}, {"Location": [["214.5", "186.3"], ["220.4", "186.3"], ["220.4", "275.7"], ["214.5", "275.7"]], "Type": "SD"}], "Module": "M15", "Boundary": [["224.5", "181.2"], ["224.5", "280.8"], ["223.9", "280.8"], ["223.9", "297.5"], ["10.0", "297.5"], ["10.0", "181.2"]], "Module_type": "GATE"}, {"Ports": [{"Location": [["26.3", "1051.6"], ["88.4", "1051.6"], ["88.4", "1056.5"], ["26.3", "1056.5"]], "Type": "SD"}, {"Location": [["10.0", "955.2"], ["104.7", "955.2"], ["104.7", "1049.9"], ["10.0", "1049.9"]], "Type": "GATE"}, {"Location": [["16.8", "961.0"], ["97.9", "961.0"], ["97.9", "968.1"], ["16.8", "968.1"]], "Type": "SD"}], "Module": "M12", "Boundary": [["10.0", "955.2"], ["104.7", "955.2"], ["104.7", "1056.5"], ["10.0", "1056.5"]], "Module_type": "GATE"}, {"Ports": [{"Location": [["285.3", "924.1"], ["309.4", "924.1"], ["309.4", "928.8"], ["285.3", "928.8"]], "Type": "SD"}, {"Location": [["271.4", "800.1"], ["306.3", "800.1"], ["306.3", "800.2"], ["323.3", "800.2"], ["323.3", "921.1"], ["271.4", "921.1"]], "Type": "GATE"}, {"Location": [["276.8", "804.5"], ["300.9", "804.5"], ["300.9", "810.9"], ["276.8", "810.9"]], "Type": "SD"}], "Module": "M8", "Boundary": [["271.4", "800.1"], ["306.3", "800.1"], ["306.3", "800.2"], ["323.3", "800.2"], ["323.3", "928.8"], ["271.4", "928.8"]], "Module_type": "GATE"}], "Area": [["-30.0", "-20.0"], ["384.1", "-20.0"], ["384.1", "1099.9"], ["-30.0", "1099.9"]], "Rules": ["GATE(5,5)", "SD(5,5)", "GATE_SD(0.5)", "GATE_ITO(0.5)", "SD_ITO(0.5)"]}