{"Modules": [{"Module": "M14", "Boundary": [["591.8", "625.9"], ["591.8", "740.1"], ["539.5", "740.1"], ["539.5", "752.8"], ["393.8", "752.8"], ["393.8", "625.9"]], "Module_type": "GATE", "Ports": [{"Location": [["393.8", "638.1"], ["399.5", "638.1"], ["399.5", "740.6"], ["393.8", "740.6"]], "Type": "SD"}, {"Location": [["591.8", "625.9"], ["591.8", "740.1"], ["539.5", "740.1"], ["539.5", "752.8"], ["401.5", "752.8"], ["401.5", "625.9"]], "Type": "GATE"}, {"Location": [["581.3", "631.9"], ["586.8", "631.9"], ["586.8", "733.1"], ["581.3", "733.1"]], "Type": "SD"}]}, {"Ports": [{"Location": [["349.2", "164.3"], ["473.6", "164.3"], ["473.6", "169.9"], ["349.2", "169.9"]], "Type": "SD"}, {"Location": [["335.1", "20.0"], ["487.7", "20.0"], ["487.7", "163.3"], ["335.1", "163.3"]], "Type": "GATE"}, {"Location": [["341.9", "25.8"], ["480.9", "25.8"], ["480.9", "31.3"], ["341.9", "31.3"]], "Type": "SD"}], "Module": "M9", "Boundary": [["335.1", "20.0"], ["487.7", "20.0"], ["487.7", "169.9"], ["335.1", "169.9"]], "Module_type": "GATE"}, {"Ports": [{"Location": [["111.8", "165.5"], ["150.5", "165.5"], ["150.5", "170.7"], ["111.8", "170.7"]], "Type": "SD"}, {"Location": [["99.5", "10.0"], ["147.2", "10.0"], ["147.2", "10.2"], ["162.8", "10.2"], ["162.8", "164.2"], ["99.5", "164.2"]], "Type": "GATE"}, {"Location": [["104.6", "14.1"], ["142.1", "14.1"], ["142.1", "20.6"], ["104.6", "20.6"]], "Type": "SD"}], "Module": "M5", "Boundary": [["99.5", "10.0"], ["147.2", "10.0"], ["147.2", "10.2"], ["162.8", "10.2"], ["162.8", "170.7"], ["99.5", "170.7"]], "Module_type": "GATE"}, {"Ports": [{"Location": [["158.9", "399.8"], ["164.6", "399.8"], ["164.6", "439.4"], ["158.9", "439.4"]], "Type": "SD"}, {"Location": [["291.1", "386.4"], ["291.1", "436.7"], ["290.8", "436.7"], ["290.8", "452.8"], ["165.8", "452.8"], ["165.8", "386.4"]], "Type": "GATE"}, {"Location": [["280.4", "392.7"], ["285.8", "392.7"], ["285.8", "430.4"], ["280.4", "430.4"]], "Type": "SD"}], "Module": "M11", "Boundary": [["291.1", "386.4"], ["291.1", "436.7"], ["290.8", "436.7"], ["290.8", "452.8"], ["158.9", "452.8"], ["158.9", "386.4"]], "Module_type": "GATE"}, {"Ports": [{"Location": [["351.9", "914.2"], ["403.6", "914.2"], ["403.6", "918.9"], ["351.9", "918.9"]], "Type": "SD"}, {"Location": [["341.3", "776.8"], ["414.2", "776.8"], ["414.2", "912.4"], ["341.3", "912.4"]], "Type": "GATE"}, {"Location": [["346.4", "780.9"], ["409.1", "780.9"], ["409.1", "785.6"], ["346.4", "785.6"]], "Type": "SD"}], "Module": "M1", "Boundary": [["341.3", "776.8"], ["414.2", "776.8"], ["414.2", "918.9"], ["341.3", "918.9"]], "Module_type": "GATE"}, {"Ports": [{"Location": [["43.4", "465.6"], ["95.5", "465.6"], ["95.5", "471.1"], ["43.4", "471.1"]], "Type": "SD"}, {"Location": [["30.0", "254.1"], ["93.6", "254.1"], ["93.6", "254.4"], ["108.9", "254.4"], ["108.9", "463.9"], ["30.0", "463.9"]], "Type": "GATE"}, {"Location": [["35.1", "258.2"], ["88.5", "258.2"], ["88.5", "265.2"], ["35.1", "265.2"]], "Type": "SD"}], "Module": "M19", "Boundary": [["30.0", "254.1"], ["93.6", "254.1"], ["93.6", "254.4"], ["108.9", "254.4"], ["108.9", "471.1"], ["30.0", "471.1"]], "Module_type": "GATE"}, {"Ports": [{"Location": [["23.8", "707.1"], ["113.8", "707.1"], ["113.8", "711.8"], ["23.8", "711.8"]], "Type": "SD"}, {"Location": [["10.0", "605.1"], ["111.9", "605.1"], ["111.9", "653.7"], ["127.6", "653.7"], ["127.6", "704.5"], ["10.0", "704.5"]], "Type": "GATE"}, {"Location": [["15.9", "610.0"], ["105.0", "610.0"], ["105.0", "616.1"], ["15.9", "616.1"]], "Type": "SD"}], "Module": "M6", "Boundary": [["10.0", "605.1"], ["111.9", "605.1"], ["111.9", "653.7"], ["127.6", "653.7"], ["127.6", "711.8"], ["10.0", "711.8"]], "Module_type": "GATE"}, {"Ports": [{"Location": [["434.2", "787.6"], ["438.5", "787.6"], ["438.5", "919.3"], ["434.2", "919.3"]], "Type": "SD"}, {"Location": [["606.6", "772.8"], ["606.6", "917.3"], ["547.0", "917.3"], ["547.0", "934.1"], ["440.2", "934.1"], ["440.2", "772.8"]], "Type": "GATE"}, {"Location": [["594.9", "778.7"], ["601.7", "778.7"], ["601.7", "910.4"], ["594.9", "910.4"]], "Type": "SD"}], "Module": "M2", "Boundary": [["606.6", "772.8"], ["606.6", "917.3"], ["547.0", "917.3"], ["547.0", "934.1"], ["434.2", "934.1"], ["434.2", "772.8"]], "Module_type": "GATE"}, {"Ports": [{"Location": [["385.2", "494.5"], ["389.3", "494.5"], ["389.3", "572.1"], ["385.2", "572.1"]], "Type": "SD"}, {"Location": [["579.8", "480.7"], ["579.8", "572.7"], ["528.6", "572.7"], ["528.6", "585.9"], ["390.5", "585.9"], ["390.5", "480.7"]], "Type": "GATE"}, {"Location": [["567.8", "487.3"], ["574.2", "487.3"], ["574.2", "565.1"], ["567.8", "565.1"]], "Type": "SD"}], "Module": "M16", "Boundary": [["579.8", "480.7"], ["579.8", "572.7"], ["528.6", "572.7"], ["528.6", "585.9"], ["385.2", "585.9"], ["385.2", "480.7"]], "Module_type": "GATE"}, {"Ports": [{"Location": [["216.8", "197.5"], ["271.1", "197.5"], ["271.1", "201.7"], ["216.8", "201.7"]], "Type": "SD"}, {"Location": [["202.8", "30.0"], ["285.1", "30.0"], ["285.1", "194.9"], ["202.8", "194.9"]], "Type": "GATE"}, {"Location": [["209.2", "35.4"], ["278.7", "35.4"], ["278.7", "41.1"], ["209.2", "41.1"]], "Type": "SD"}], "Module": "M13", "Boundary": [["202.8", "30.0"], ["285.1", "30.0"], ["285.1", "201.7"], ["202.8", "201.7"]], "Module_type": "GATE"}, {"Ports": [{"Location": [["484.6", "426.1"], ["583.8", "426.1"], ["583.8", "430.7"], ["484.6", "430.7"]], "Type": "SD"}, {"Location": [["471.0", "244.5"], ["583.0", "244.5"], ["583.0", "340.8"], ["597.4", "340.8"], ["597.4", "423.3"], ["471.0", "423.3"]], "Type": "GATE"}, {"Location": [["477.3", "249.8"], ["575.7", "249.8"], ["575.7", "255.4"], ["477.3", "255.4"]], "Type": "SD"}], "Module": "M10", "Boundary": [["471.0", "244.5"], ["583.0", "244.5"], ["583.0", "340.8"], ["597.4", "340.8"], ["597.4", "430.7"], ["471.0", "430.7"]], "Module_type": "GATE"}, {"Ports": [{"Location": [["147.6", "654.1"], ["151.8", "654.1"], ["151.8", "744.0"], ["147.6", "744.0"]], "Type": "SD"}, {"Location": [["373.8", "641.3"], ["373.8", "756.8"], ["154.5", "756.8"], ["154.5", "641.3"]], "Type": "GATE"}, {"Location": [["363.9", "647.3"], ["368.8", "647.3"], ["368.8", "750.8"], ["363.9", "750.8"]], "Type": "SD"}], "Module": "M7", "Boundary": [["373.8", "641.3"], ["373.8", "756.8"], ["147.6", "756.8"], ["147.6", "641.3"]], "Module_type": "GATE"}, {"Ports": [{"Location": [["358.2", "408.9"], ["407.9", "408.9"], ["407.9", "414.0"], ["358.2", "414.0"]], "Type": "SD"}, {"Location": [["345.1", "219.9"], ["421.0", "219.9"], ["421.0", "407.7"], ["345.1", "407.7"]], "Type": "GATE"}, {"Location": [["350.3", "224.1"], ["415.8", "224.1"], ["415.8", "231.0"], ["350.3", "231.0"]], "Type": "SD"}], "Module": "M3", "Boundary": [["345.1", "219.9"], ["421.0", "219.9"], ["421.0", "414.0"], ["345.1", "414.0"]], "Module_type": "GATE"}, {"Ports": [{"Location": [["190.9", "495.6"], ["196.1", "495.6"], ["196.1", "608.5"], ["190.9", "608.5"]], "Type": "SD"}, {"Location": [["345.2", "482.8"], ["345.2", "607.2"], ["319.5", "607.2"], ["319.5", "621.3"], ["197.6", "621.3"], ["197.6", "482.8"]], "Type": "GATE"}, {"Location": [["334.1", "488.7"], ["340.3", "488.7"], ["340.3", "600.3"], ["334.1", "600.3"]], "Type": "SD"}], "Module": "M18", "Boundary": [["345.2", "482.8"], ["345.2", "607.2"], ["319.5", "607.2"], ["319.5", "621.3"], ["190.9", "621.3"], ["190.9", "482.8"]], "Module_type": "GATE"}, {"Ports": [{"Location": [["130.9", "808.2"], ["135.3", "808.2"], ["135.3", "904.3"], ["130.9", "904.3"]], "Type": "SD"}, {"Location": [["301.3", "796.8"], ["301.3", "901.9"], ["226.8", "901.9"], ["226.8", "915.7"], ["137.0", "915.7"], ["137.0", "796.8"]], "Type": "GATE"}, {"Location": [["291.6", "802.1"], ["297.0", "802.1"], ["297.0", "895.6"], ["291.6", "895.6"]], "Type": "SD"}], "Module": "M20", "Boundary": [["301.3", "796.8"], ["301.3", "901.9"], ["226.8", "901.9"], ["226.8", "915.7"], ["130.9", "915.7"], ["130.9", "796.8"]], "Module_type": "GATE"}, {"Ports": [{"Location": [["24.3", "208.8"], ["65.2", "208.8"], ["65.2", "214.1"], ["24.3", "214.1"]], "Type": "SD"}, {"Location": [["10.0", "10.0"], ["62.3", "10.0"], ["62.3", "10.3"], ["79.5", "10.3"], ["79.5", "206.2"], ["10.0", "206.2"]], "Type": "GATE"}, {"Location": [["15.3", "14.3"], ["57.0", "14.3"], ["57.0", "20.9"], ["15.3", "20.9"]], "Type": "SD"}], "Module": "M15", "Boundary": [["10.0", "10.0"], ["62.3", "10.0"], ["62.3", "10.3"], ["79.5", "10.3"], ["79.5", "214.1"], ["10.0", "214.1"]], "Module_type": "GATE"}, {"Ports": [{"Location": [["531.4", "208.6"], ["581.5", "208.6"], ["581.5", "214.5"], ["531.4", "214.5"]], "Type": "SD"}, {"Location": [["517.7", "10.0"], ["581.8", "10.0"], ["581.8", "80.6"], ["595.2", "80.6"], ["595.2", "205.8"], ["517.7", "205.8"]], "Type": "GATE"}, {"Location": [["524.0", "15.3"], ["574.5", "15.3"], ["574.5", "21.7"], ["524.0", "21.7"]], "Type": "SD"}], "Module": "M12", "Boundary": [["517.7", "10.0"], ["581.8", "10.0"], ["581.8", "80.6"], ["595.2", "80.6"], ["595.2", "214.5"], ["517.7", "214.5"]], "Module_type": "GATE"}, {"Ports": [{"Location": [["22.3", "928.2"], ["78.6", "928.2"], ["78.6", "933.3"], ["22.3", "933.3"]], "Type": "SD"}, {"Location": [["10.0", "731.8"], ["75.6", "731.8"], ["75.6", "856.5"], ["90.9", "856.5"], ["90.9", "926.3"], ["10.0", "926.3"]], "Type": "GATE"}, {"Location": [["15.5", "736.3"], ["69.1", "736.3"], ["69.1", "741.3"], ["15.5", "741.3"]], "Type": "SD"}], "Module": "M8", "Boundary": [["10.0", "731.8"], ["75.6", "731.8"], ["75.6", "856.5"], ["90.9", "856.5"], ["90.9", "933.3"], ["10.0", "933.3"]], "Module_type": "GATE"}, {"Ports": [{"Location": [["182.8", "254.7"], ["187.9", "254.7"], ["187.9", "343.4"], ["182.8", "343.4"]], "Type": "SD"}, {"Location": [["298.7", "241.7"], ["298.7", "341.0"], ["234.3", "341.0"], ["234.3", "356.4"], ["189.3", "356.4"], ["189.3", "241.7"]], "Type": "GATE"}, {"Location": [["288.7", "247.2"], ["294.2", "247.2"], ["294.2", "334.5"], ["288.7", "334.5"]], "Type": "SD"}], "Module": "M4", "Boundary": [["298.7", "241.7"], ["298.7", "341.0"], ["234.3", "341.0"], ["234.3", "356.4"], ["182.8", "356.4"], ["182.8", "241.7"]], "Module_type": "GATE"}, {"Ports": [{"Location": [["10.0", "522.1"], ["14.5", "522.1"], ["14.5", "574.1"], ["10.0", "574.1"]], "Type": "SD"}, {"Location": [["170.9", "511.1"], ["170.9", "585.1"], ["16.1", "585.1"], ["16.1", "511.1"]], "Type": "GATE"}, {"Location": [["161.7", "516.5"], ["166.5", "516.5"], ["166.5", "579.7"], ["161.7", "579.7"]], "Type": "SD"}], "Module": "M17", "Boundary": [["170.9", "511.1"], ["170.9", "585.1"], ["10.0", "585.1"], ["10.0", "511.1"]], "Module_type": "GATE"}], "Area": [["-30.0", "-30.0"], ["646.6", "-30.0"], ["646.6", "974.1"], ["-30.0", "974.1"]], "Rules": ["GATE(5,5)", "SD(5,5)", "GATE_SD(0.5)", "GATE_ITO(0.5)", "SD_ITO(0.5)"]}