{"Modules": [{"Module": "M14", "Boundary": [["10.0", "250.0"], ["100.1", "250.0"], ["100.1", "380.9"], ["113.7", "380.9"], ["113.7", "460.6"], ["10.0", "460.6"]], "Module_type": "GATE", "Ports": [{"Location": [["21.8", "454.8"], ["101.9", "454.8"], ["101.9", "460.6"], ["21.8", "460.6"]], "Type": "SD"}, {"Location": [["10.0", "250.0"], ["100.1", "250.0"], ["100.1", "380.9"], ["113.7", "380.9"], ["113.7", "452.8"], ["10.0", "452.8"]], "Type": "GATE"}, {"Location": [["15.8", "254.8"], ["93.3", "254.8"], ["93.3", "260.2"], ["15.8", "260.2"]], "Type": "SD"}]}, {"Ports": [{"Location": [["817.4", "318.7"], ["822.2", "318.7"], ["822.2", "434.3"], ["817.4", "434.3"]], "Type": "SD"}, {"Location": [["1037.1", "304.2"], ["1037.1", "430.8"], ["1036.9", "430.8"], ["1036.9", "448.8"], ["824.0", "448.8"], ["824.0", "304.2"]], "Type": "GATE"}, {"Location": [["1025.6", "309.9"], ["1032.4", "309.9"], ["1032.4", "425.1"], ["1025.6", "425.1"]], "Type": "SD"}], "Module": "M9", "Boundary": [["1037.1", "304.2"], ["1037.1", "430.8"], ["1036.9", "430.8"], ["1036.9", "448.8"], ["817.4", "448.8"], ["817.4", "304.2"]], "Module_type": "GATE"}, {"Ports": [{"Location": [["819.3", "195.4"], ["823.7", "195.4"], ["823.7", "261.2"], ["819.3", "261.2"]], "Type": "SD"}, {"Location": [["997.1", "182.4"], ["997.1", "274.2"], ["826.0", "274.2"], ["826.0", "182.4"]], "Type": "GATE"}, {"Location": [["986.2", "188.1"], ["992.4", "188.1"], ["992.4", "268.5"], ["986.2", "268.5"]], "Type": "SD"}], "Module": "M5", "Boundary": [["997.1", "182.4"], ["997.1", "274.2"], ["819.3", "274.2"], ["819.3", "182.4"]], "Module_type": "GATE"}, {"Ports": [{"Location": [["602.0", "269.0"], ["654.1", "269.0"], ["654.1", "273.7"], ["602.0", "273.7"]], "Type": "SD"}, {"Location": [["590.0", "178.5"], ["666.1", "178.5"], ["666.1", "266.9"], ["590.0", "266.9"]], "Type": "GATE"}, {"Location": [["595.1", "182.6"], ["661.0", "182.6"], ["661.0", "188.1"], ["595.1", "188.1"]], "Type": "SD"}], "Module": "M11", "Boundary": [["590.0", "178.5"], ["666.1", "178.5"], ["666.1", "273.7"], ["590.0", "273.7"]], "Module_type": "GATE"}, {"Ports": [{"Location": [["1017.1", "195.5"], ["1021.5", "195.5"], ["1021.5", "252.3"], ["1017.1", "252.3"]], "Type": "SD"}, {"Location": [["1182.9", "182.4"], ["1182.9", "265.4"], ["1024.2", "265.4"], ["1024.2", "182.4"]], "Type": "GATE"}, {"Location": [["1172.0", "187.7"], ["1178.6", "187.7"], ["1178.6", "260.1"], ["1172.0", "260.1"]], "Type": "SD"}], "Module": "M1", "Boundary": [["1182.9", "182.4"], ["1182.9", "265.4"], ["1017.1", "265.4"], ["1017.1", "182.4"]], "Module_type": "GATE"}, {"Ports": [{"Location": [["408.3", "214.5"], ["526.1", "214.5"], ["526.1", "220.0"], ["408.3", "220.0"]], "Type": "SD"}, {"Location": [["394.4", "30.0"], ["521.6", "30.0"], ["521.6", "30.4"], ["540.0", "30.4"], ["540.0", "213.3"], ["394.4", "213.3"]], "Type": "GATE"}, {"Location": [["400.1", "34.7"], ["515.9", "34.7"], ["515.9", "40.4"], ["400.1", "40.4"]], "Type": "SD"}], "Module": "M19", "Boundary": [["394.4", "30.0"], ["521.6", "30.0"], ["521.6", "30.4"], ["540.0", "30.4"], ["540.0", "220.0"], ["394.4", "220.0"]], "Module_type": "GATE"}, {"Ports": [{"Location": [["673.2", "22.1"], ["677.6", "22.1"], ["677.6", "136.4"], ["673.2", "136.4"]], "Type": "SD"}, {"Location": [["799.3", "10.0"], ["799.3", "134.3"], ["737.7", "134.3"], ["737.7", "148.5"], ["680.3", "148.5"], ["680.3", "10.0"]], "Type": "GATE"}, {"Location": [["789.2", "15.5"], ["794.8", "15.5"], ["794.8", "127.8"], ["789.2", "127.8"]], "Type": "SD"}], "Module": "M6", "Boundary": [["799.3", "10.0"], ["799.3", "134.3"], ["737.7", "134.3"], ["737.7", "148.5"], ["673.2", "148.5"], ["673.2", "10.0"]], "Module_type": "GATE"}, {"Ports": [{"Location": [["144.4", "378.9"], ["149.3", "378.9"], ["149.3", "431.4"], ["144.4", "431.4"]], "Type": "SD"}, {"Location": [["350.1", "365.5"], ["350.1", "430.7"], ["243.2", "430.7"], ["243.2", "444.8"], ["152.3", "444.8"], ["152.3", "365.5"]], "Type": "GATE"}, {"Location": [["338.5", "372.2"], ["344.4", "372.2"], ["344.4", "423.0"], ["338.5", "423.0"]], "Type": "SD"}], "Module": "M2", "Boundary": [["350.1", "365.5"], ["350.1", "430.7"], ["243.2", "430.7"], ["243.2", "444.8"], ["144.4", "444.8"], ["144.4", "365.5"]], "Module_type": "GATE"}, {"Ports": [{"Location": [["164.4", "196.8"], ["168.9", "196.8"], ["168.9", "312.0"], ["164.4", "312.0"]], "Type": "SD"}, {"Location": [["323.9", "183.3"], ["323.9", "308.6"], ["282.7", "308.6"], ["282.7", "325.5"], ["170.7", "325.5"], ["170.7", "183.3"]], "Type": "GATE"}, {"Location": [["313.1", "189.0"], ["319.2", "189.0"], ["319.2", "301.9"], ["313.1", "301.9"]], "Type": "SD"}], "Module": "M16", "Boundary": [["323.9", "183.3"], ["323.9", "308.6"], ["282.7", "308.6"], ["282.7", "325.5"], ["164.4", "325.5"], ["164.4", "183.3"]], "Module_type": "GATE"}, {"Ports": [{"Location": [["42.6", "204.6"], ["91.8", "204.6"], ["91.8", "210.0"], ["42.6", "210.0"]], "Type": "SD"}, {"Location": [["30.0", "30.0"], ["90.2", "30.0"], ["90.2", "30.2"], ["104.4", "30.2"], ["104.4", "203.2"], ["30.0", "203.2"]], "Type": "GATE"}, {"Location": [["35.8", "34.8"], ["84.4", "34.8"], ["84.4", "40.9"], ["35.8", "40.9"]], "Type": "SD"}], "Module": "M13", "Boundary": [["30.0", "30.0"], ["90.2", "30.0"], ["90.2", "30.2"], ["104.4", "30.2"], ["104.4", "210.0"], ["30.0", "210.0"]], "Module_type": "GATE"}, {"Ports": [{"Location": [["829.3", "32.6"], ["833.9", "32.6"], ["833.9", "136.1"], ["829.3", "136.1"]], "Type": "SD"}, {"Location": [["957.3", "20.0"], ["957.3", "133.7"], ["905.8", "133.7"], ["905.8", "148.7"], ["836.9", "148.7"], ["836.9", "20.0"]], "Type": "GATE"}, {"Location": [["947.3", "25.2"], ["953.1", "25.2"], ["953.1", "127.5"], ["947.3", "127.5"]], "Type": "SD"}], "Module": "M10", "Boundary": [["957.3", "20.0"], ["957.3", "133.7"], ["905.8", "133.7"], ["905.8", "148.7"], ["829.3", "148.7"], ["829.3", "20.0"]], "Module_type": "GATE"}, {"Ports": [{"Location": [["713.8", "434.4"], ["775.0", "434.4"], ["775.0", "438.7"], ["713.8", "438.7"]], "Type": "SD"}, {"Location": [["702.2", "288.8"], ["786.6", "288.8"], ["786.6", "433.0"], ["702.2", "433.0"]], "Type": "GATE"}, {"Location": [["707.2", "292.8"], ["781.6", "292.8"], ["781.6", "298.3"], ["707.2", "298.3"]], "Type": "SD"}], "Module": "M7", "Boundary": [["702.2", "288.8"], ["786.6", "288.8"], ["786.6", "438.7"], ["702.2", "438.7"]], "Module_type": "GATE"}, {"Ports": [{"Location": [["1007.3", "43.7"], ["1012.2", "43.7"], ["1012.2", "128.7"], ["1007.3", "128.7"]], "Type": "SD"}, {"Location": [["1174.6", "30.0"], ["1174.6", "142.4"], ["1013.4", "142.4"], ["1013.4", "30.0"]], "Type": "GATE"}, {"Location": [["1164.4", "35.1"], ["1170.5", "35.1"], ["1170.5", "137.3"], ["1164.4", "137.3"]], "Type": "SD"}], "Module": "M3", "Boundary": [["1174.6", "30.0"], ["1174.6", "142.4"], ["1007.3", "142.4"], ["1007.3", "30.0"]], "Module_type": "GATE"}, {"Ports": [{"Location": [["284.0", "132.3"], ["343.3", "132.3"], ["343.3", "137.0"], ["284.0", "137.0"]], "Type": "SD"}, {"Location": [["272.9", "10.0"], ["342.2", "10.0"], ["342.2", "20.5"], ["354.4", "20.5"], ["354.4", "130.6"], ["272.9", "130.6"]], "Type": "GATE"}, {"Location": [["278.2", "14.3"], ["335.9", "14.3"], ["335.9", "19.4"], ["278.2", "19.4"]], "Type": "SD"}], "Module": "M18", "Boundary": [["272.9", "10.0"], ["342.2", "10.0"], ["342.2", "20.5"], ["354.4", "20.5"], ["354.4", "137.0"], ["272.9", "137.0"]], "Module_type": "GATE"}, {"Ports": [{"Location": [["573.0", "425.4"], ["648.7", "425.4"], ["648.7", "430.7"], ["573.0", "430.7"]], "Type": "SD"}, {"Location": [["559.5", "323.7"], ["646.1", "323.7"], ["646.1", "331.3"], ["662.2", "331.3"], ["662.2", "422.7"], ["559.5", "422.7"]], "Type": "GATE"}, {"Location": [["565.7", "328.9"], ["638.9", "328.9"], ["638.9", "334.2"], ["565.7", "334.2"]], "Type": "SD"}], "Module": "M20", "Boundary": [["559.5", "323.7"], ["646.1", "323.7"], ["646.1", "331.3"], ["662.2", "331.3"], ["662.2", "430.7"], ["559.5", "430.7"]], "Module_type": "GATE"}, {"Ports": [{"Location": [["1082.0", "441.7"], ["1177.1", "441.7"], ["1177.1", "447.5"], ["1082.0", "447.5"]], "Type": "SD"}, {"Location": [["1067.1", "285.4"], ["1192.0", "285.4"], ["1192.0", "440.7"], ["1067.1", "440.7"]], "Type": "GATE"}, {"Location": [["1072.6", "289.9"], ["1186.5", "289.9"], ["1186.5", "297.2"], ["1072.6", "297.2"]], "Type": "SD"}], "Module": "M15", "Boundary": [["1067.1", "285.4"], ["1192.0", "285.4"], ["1192.0", "447.5"], ["1067.1", "447.5"]], "Module_type": "GATE"}, {"Ports": [{"Location": [["387.7", "445.9"], ["506.2", "445.9"], ["506.2", "451.9"], ["387.7", "451.9"]], "Type": "SD"}, {"Location": [["374.4", "260.0"], ["504.6", "260.0"], ["504.6", "359.1"], ["519.5", "359.1"], ["519.5", "443.5"], ["374.4", "443.5"]], "Type": "GATE"}, {"Location": [["380.6", "265.2"], ["497.4", "265.2"], ["497.4", "271.3"], ["380.6", "271.3"]], "Type": "SD"}], "Module": "M12", "Boundary": [["374.4", "260.0"], ["504.6", "260.0"], ["504.6", "359.1"], ["519.5", "359.1"], ["519.5", "451.9"], ["374.4", "451.9"]], "Module_type": "GATE"}, {"Ports": [{"Location": [["156.9", "138.7"], ["240.4", "138.7"], ["240.4", "143.3"], ["156.9", "143.3"]], "Type": "SD"}, {"Location": [["144.4", "10.0"], ["238.8", "10.0"], ["238.8", "76.3"], ["252.9", "76.3"], ["252.9", "137.3"], ["144.4", "137.3"]], "Type": "GATE"}, {"Location": [["150.5", "15.1"], ["231.7", "15.1"], ["231.7", "20.7"], ["150.5", "20.7"]], "Type": "SD"}], "Module": "M8", "Boundary": [["144.4", "10.0"], ["238.8", "10.0"], ["238.8", "76.3"], ["252.9", "76.3"], ["252.9", "143.3"], ["144.4", "143.3"]], "Module_type": "GATE"}, {"Ports": [{"Location": [["591.3", "121.0"], ["641.9", "121.0"], ["641.9", "125.3"], ["591.3", "125.3"]], "Type": "SD"}, {"Location": [["580.0", "10.0"], ["639.8", "10.0"], ["639.8", "19.0"], ["653.2", "19.0"], ["653.2", "118.6"], ["580.0", "118.6"]], "Type": "GATE"}, {"Location": [["585.2", "14.2"], ["633.6", "14.2"], ["633.6", "19.5"], ["585.2", "19.5"]], "Type": "SD"}], "Module": "M4", "Boundary": [["580.0", "10.0"], ["639.8", "10.0"], ["639.8", "19.0"], ["653.2", "19.0"], ["653.2", "125.3"], ["580.0", "125.3"]], "Module_type": "GATE"}, {"Ports": [{"Location": [["709.6", "264.2"], ["773.9", "264.2"], ["773.9", "268.8"], ["709.6", "268.8"]], "Type": "SD"}, {"Location": [["696.1", "168.5"], ["787.4", "168.5"], ["787.4", "262.9"], ["696.1", "262.9"]], "Type": "GATE"}, {"Location": [["702.5", "173.9"], ["781.0", "173.9"], ["781.0", "180.3"], ["702.5", "180.3"]], "Type": "SD"}], "Module": "M17", "Boundary": [["696.1", "168.5"], ["787.4", "168.5"], ["787.4", "268.8"], ["696.1", "268.8"]], "Module_type": "GATE"}], "Area": [["-30.0", "-30.0"], ["1232.0", "-30.0"], ["1232.0", "500.6"], ["-30.0", "500.6"]], "Rules": ["GATE(5,5)", "SD(5,5)", "GATE_SD(0.5)", "GATE_ITO(0.5)", "SD_ITO(0.5)"]}