{"Modules": [{"Module": "M14", "Boundary": [["573.0", "338.0"], ["633.6", "338.0"], ["633.6", "408.5"], ["647.4", "408.5"], ["647.4", "479.3"], ["573.0", "479.3"]], "Module_type": "GATE", "Ports": [{"Location": [["584.8", "474.8"], ["635.6", "474.8"], ["635.6", "479.3"], ["584.8", "479.3"]], "Type": "SD"}, {"Location": [["573.0", "338.0"], ["633.6", "338.0"], ["633.6", "408.5"], ["647.4", "408.5"], ["647.4", "472.5"], ["573.0", "472.5"]], "Type": "GATE"}, {"Location": [["578.7", "342.7"], ["626.9", "342.7"], ["626.9", "347.3"], ["578.7", "347.3"]], "Type": "SD"}]}, {"Ports": [{"Location": [["341.4", "217.5"], ["398.5", "217.5"], ["398.5", "221.7"], ["341.4", "221.7"]], "Type": "SD"}, {"Location": [["328.6", "20.0"], ["411.3", "20.0"], ["411.3", "214.8"], ["328.6", "214.8"]], "Type": "GATE"}, {"Location": [["334.7", "25.1"], ["405.2", "25.1"], ["405.2", "30.1"], ["334.7", "30.1"]], "Type": "SD"}], "Module": "M9", "Boundary": [["328.6", "20.0"], ["411.3", "20.0"], ["411.3", "221.7"], ["328.6", "221.7"]], "Module_type": "GATE"}, {"Ports": [{"Location": [["441.5", "493.3"], ["539.8", "493.3"], ["539.8", "497.8"], ["441.5", "497.8"]], "Type": "SD"}, {"Location": [["429.6", "321.8"], ["536.6", "321.8"], ["536.6", "322.0"], ["551.7", "322.0"], ["551.7", "491.7"], ["429.6", "491.7"]], "Type": "GATE"}, {"Location": [["434.8", "326.0"], ["531.4", "326.0"], ["531.4", "332.2"], ["434.8", "332.2"]], "Type": "SD"}], "Module": "M5", "Boundary": [["429.6", "321.8"], ["536.6", "321.8"], ["536.6", "322.0"], ["551.7", "322.0"], ["551.7", "497.8"], ["429.6", "497.8"]], "Module_type": "GATE"}, {"Ports": [{"Location": [["814.0", "406.7"], ["819.7", "406.7"], ["819.7", "493.1"], ["814.0", "493.1"]], "Type": "SD"}, {"Location": [["1037.5", "393.7"], ["1037.5", "506.1"], ["820.9", "506.1"], ["820.9", "393.7"]], "Type": "GATE"}, {"Location": [["1026.4", "400.2"], ["1032.0", "400.2"], ["1032.0", "499.6"], ["1026.4", "499.6"]], "Type": "SD"}], "Module": "M11", "Boundary": [["1037.5", "393.7"], ["1037.5", "506.1"], ["814.0", "506.1"], ["814.0", "393.7"]], "Module_type": "GATE"}, {"Ports": [{"Location": [["681.7", "503.5"], ["769.7", "503.5"], ["769.7", "509.4"], ["681.7", "509.4"]], "Type": "SD"}, {"Location": [["667.4", "338.0"], ["767.8", "338.0"], ["767.8", "338.6"], ["784.0", "338.6"], ["784.0", "501.3"], ["667.4", "501.3"]], "Type": "GATE"}, {"Location": [["674.3", "343.9"], ["760.9", "343.9"], ["760.9", "349.7"], ["674.3", "349.7"]], "Type": "SD"}], "Module": "M1", "Boundary": [["667.4", "338.0"], ["767.8", "338.0"], ["767.8", "338.6"], ["784.0", "338.6"], ["784.0", "509.4"], ["667.4", "509.4"]], "Module_type": "GATE"}, {"Ports": [{"Location": [["42.1", "168.7"], ["143.3", "168.7"], ["143.3", "172.9"], ["42.1", "172.9"]], "Type": "SD"}, {"Location": [["30.0", "30.0"], ["139.8", "30.0"], ["139.8", "30.5"], ["155.4", "30.5"], ["155.4", "166.5"], ["30.0", "166.5"]], "Type": "GATE"}, {"Location": [["35.1", "34.1"], ["134.7", "34.1"], ["134.7", "40.4"], ["35.1", "40.4"]], "Type": "SD"}], "Module": "M19", "Boundary": [["30.0", "30.0"], ["139.8", "30.0"], ["139.8", "30.5"], ["155.4", "30.5"], ["155.4", "172.9"], ["30.0", "172.9"]], "Module_type": "GATE"}, {"Ports": [{"Location": [["920.9", "22.6"], ["926.1", "22.6"], ["926.1", "98.1"], ["920.9", "98.1"]], "Type": "SD"}, {"Location": [["1035.9", "10.0"], ["1035.9", "97.9"], ["1000.1", "97.9"], ["1000.1", "110.7"], ["928.1", "110.7"], ["928.1", "10.0"]], "Type": "GATE"}, {"Location": [["1024.9", "15.2"], ["1031.7", "15.2"], ["1031.7", "91.7"], ["1024.9", "91.7"]], "Type": "SD"}], "Module": "M6", "Boundary": [["1035.9", "10.0"], ["1035.9", "97.9"], ["1000.1", "97.9"], ["1000.1", "110.7"], ["920.9", "110.7"], ["920.9", "10.0"]], "Module_type": "GATE"}, {"Ports": [{"Location": [["803.3", "190.3"], ["888.0", "190.3"], ["888.0", "196.3"], ["803.3", "196.3"]], "Type": "SD"}, {"Location": [["790.4", "10.0"], ["900.9", "10.0"], ["900.9", "188.1"], ["790.4", "188.1"]], "Type": "GATE"}, {"Location": [["797.3", "15.9"], ["894.0", "15.9"], ["894.0", "20.9"], ["797.3", "20.9"]], "Type": "SD"}], "Module": "M2", "Boundary": [["790.4", "10.0"], ["900.9", "10.0"], ["900.9", "196.3"], ["790.4", "196.3"]], "Module_type": "GATE"}, {"Ports": [{"Location": [["461.3", "44.1"], ["466.0", "44.1"], ["466.0", "158.4"], ["461.3", "158.4"]], "Type": "SD"}, {"Location": [["564.8", "30.0"], ["564.8", "158.1"], ["534.3", "158.1"], ["534.3", "172.5"], ["468.5", "172.5"], ["468.5", "30.0"]], "Type": "GATE"}, {"Location": [["553.1", "37.0"], ["558.8", "37.0"], ["558.8", "150.1"], ["553.1", "150.1"]], "Type": "SD"}], "Module": "M16", "Boundary": [["564.8", "30.0"], ["564.8", "158.1"], ["534.3", "158.1"], ["534.3", "172.5"], ["461.3", "172.5"], ["461.3", "30.0"]], "Module_type": "GATE"}, {"Ports": [{"Location": [["42.9", "367.8"], ["140.1", "367.8"], ["140.1", "373.2"], ["42.9", "373.2"]], "Type": "SD"}, {"Location": [["30.0", "232.9"], ["153.0", "232.9"], ["153.0", "365.0"], ["30.0", "365.0"]], "Type": "GATE"}, {"Location": [["35.2", "237.1"], ["147.8", "237.1"], ["147.8", "242.9"], ["35.2", "242.9"]], "Type": "SD"}], "Module": "M13", "Boundary": [["30.0", "232.9"], ["153.0", "232.9"], ["153.0", "373.2"], ["30.0", "373.2"]], "Module_type": "GATE"}, {"Ports": [{"Location": [["627.9", "180.3"], ["747.3", "180.3"], ["747.3", "185.0"], ["627.9", "185.0"]], "Type": "SD"}, {"Location": [["614.8", "20.0"], ["745.3", "20.0"], ["745.3", "33.1"], ["760.4", "33.1"], ["760.4", "178.6"], ["614.8", "178.6"]], "Type": "GATE"}, {"Location": [["620.9", "25.1"], ["738.2", "25.1"], ["738.2", "29.9"], ["620.9", "29.9"]], "Type": "SD"}], "Module": "M10", "Boundary": [["614.8", "20.0"], ["745.3", "20.0"], ["745.3", "33.1"], ["760.4", "33.1"], ["760.4", "185.0"], ["614.8", "185.0"]], "Module_type": "GATE"}, {"Ports": [{"Location": [["195.4", "444.4"], ["199.5", "444.4"], ["199.5", "500.4"], ["195.4", "500.4"]], "Type": "SD"}, {"Location": [["398.2", "432.0"], ["398.2", "512.8"], ["201.4", "512.8"], ["201.4", "432.0"]], "Type": "GATE"}, {"Location": [["387.4", "438.5"], ["392.7", "438.5"], ["392.7", "506.3"], ["387.4", "506.3"]], "Type": "SD"}], "Module": "M7", "Boundary": [["398.2", "432.0"], ["398.2", "512.8"], ["195.4", "512.8"], ["195.4", "432.0"]], "Module_type": "GATE"}, {"Ports": [{"Location": [["624.8", "248.8"], ["630.6", "248.8"], ["630.6", "285.5"], ["624.8", "285.5"]], "Type": "SD"}, {"Location": [["766.0", "236.3"], ["766.0", "283.2"], ["765.9", "283.2"], ["765.9", "298.0"], ["633.6", "298.0"], ["633.6", "236.3"]], "Type": "GATE"}, {"Location": [["755.8", "241.6"], ["761.7", "241.6"], ["761.7", "277.9"], ["755.8", "277.9"]], "Type": "SD"}], "Module": "M3", "Boundary": [["766.0", "236.3"], ["766.0", "283.2"], ["765.9", "283.2"], ["765.9", "298.0"], ["624.8", "298.0"], ["624.8", "236.3"]], "Module_type": "GATE"}, {"Ports": [{"Location": [["209.0", "224.5"], ["285.0", "224.5"], ["285.0", "230.5"], ["209.0", "230.5"]], "Type": "SD"}, {"Location": [["195.4", "10.0"], ["282.2", "10.0"], ["282.2", "49.1"], ["298.6", "49.1"], ["298.6", "222.0"], ["195.4", "222.0"]], "Type": "GATE"}, {"Location": [["200.8", "14.4"], ["275.8", "14.4"], ["275.8", "20.3"], ["200.8", "20.3"]], "Type": "SD"}], "Module": "M18", "Boundary": [["195.4", "10.0"], ["282.2", "10.0"], ["282.2", "49.1"], ["298.6", "49.1"], ["298.6", "230.5"], ["195.4", "230.5"]], "Module_type": "GATE"}, {"Ports": [{"Location": [["953.6", "338.8"], ["1013.0", "338.8"], ["1013.0", "343.7"], ["953.6", "343.7"]], "Type": "SD"}, {"Location": [["940.9", "150.7"], ["1009.2", "150.7"], ["1009.2", "218.8"], ["1025.7", "218.8"], ["1025.7", "337.7"], ["940.9", "337.7"]], "Type": "GATE"}, {"Location": [["946.2", "155.0"], ["1002.9", "155.0"], ["1002.9", "160.2"], ["946.2", "160.2"]], "Type": "SD"}], "Module": "M20", "Boundary": [["940.9", "150.7"], ["1009.2", "150.7"], ["1009.2", "218.8"], ["1025.7", "218.8"], ["1025.7", "343.7"], ["940.9", "343.7"]], "Module_type": "GATE"}, {"Ports": [{"Location": [["455.7", "296.8"], ["538.6", "296.8"], ["538.6", "301.8"], ["455.7", "301.8"]], "Type": "SD"}, {"Location": [["441.3", "212.5"], ["553.0", "212.5"], ["553.0", "295.4"], ["441.3", "295.4"]], "Type": "GATE"}, {"Location": [["447.9", "218.1"], ["546.4", "218.1"], ["546.4", "225.0"], ["447.9", "225.0"]], "Type": "SD"}], "Module": "M15", "Boundary": [["441.3", "212.5"], ["553.0", "212.5"], ["553.0", "301.8"], ["441.3", "301.8"]], "Module_type": "GATE"}, {"Ports": [{"Location": [["806.0", "230.2"], ["810.4", "230.2"], ["810.4", "330.7"], ["806.0", "330.7"]], "Type": "SD"}, {"Location": [["881.1", "216.3"], ["881.1", "332.1"], ["871.2", "332.1"], ["871.2", "344.6"], ["812.6", "344.6"], ["812.6", "216.3"]], "Type": "GATE"}, {"Location": [["869.2", "222.8"], ["875.6", "222.8"], ["875.6", "324.6"], ["869.2", "324.6"]], "Type": "SD"}], "Module": "M12", "Boundary": [["881.1", "216.3"], ["881.1", "332.1"], ["871.2", "332.1"], ["871.2", "344.6"], ["806.0", "344.6"], ["806.0", "216.3"]], "Module_type": "GATE"}, {"Ports": [{"Location": [["209.4", "407.0"], ["283.0", "407.0"], ["283.0", "412.0"], ["209.4", "412.0"]], "Type": "SD"}, {"Location": [["195.4", "250.5"], ["281.3", "250.5"], ["281.3", "291.1"], ["297.0", "291.1"], ["297.0", "404.0"], ["195.4", "404.0"]], "Type": "GATE"}, {"Location": [["202.2", "256.3"], ["273.5", "256.3"], ["273.5", "261.8"], ["202.2", "261.8"]], "Type": "SD"}], "Module": "M8", "Boundary": [["195.4", "250.5"], ["281.3", "250.5"], ["281.3", "291.1"], ["297.0", "291.1"], ["297.0", "412.0"], ["195.4", "412.0"]], "Module_type": "GATE"}, {"Ports": [{"Location": [["10.0", "425.4"], ["15.2", "425.4"], ["15.2", "503.9"], ["10.0", "503.9"]], "Type": "SD"}, {"Location": [["173.9", "413.2"], ["173.9", "502.8"], ["118.3", "502.8"], ["118.3", "516.1"], ["16.9", "516.1"], ["16.9", "413.2"]], "Type": "GATE"}, {"Location": [["163.4", "419.5"], ["168.6", "419.5"], ["168.6", "495.5"], ["163.4", "495.5"]], "Type": "SD"}], "Module": "M4", "Boundary": [["173.9", "413.2"], ["173.9", "502.8"], ["118.3", "502.8"], ["118.3", "516.1"], ["10.0", "516.1"], ["10.0", "413.2"]], "Module_type": "GATE"}, {"Ports": [{"Location": [["318.6", "266.5"], ["323.1", "266.5"], ["323.1", "378.0"], ["318.6", "378.0"]], "Type": "SD"}, {"Location": [["409.6", "251.7"], ["409.6", "375.4"], ["409.4", "375.4"], ["409.4", "392.8"], ["325.8", "392.8"], ["325.8", "251.7"]], "Type": "GATE"}, {"Location": [["397.7", "257.8"], ["404.5", "257.8"], ["404.5", "369.3"], ["397.7", "369.3"]], "Type": "SD"}], "Module": "M17", "Boundary": [["409.6", "251.7"], ["409.6", "375.4"], ["409.4", "375.4"], ["409.4", "392.8"], ["318.6", "392.8"], ["318.6", "251.7"]], "Module_type": "GATE"}], "Area": [["-30.0", "-30.0"], ["1077.5", "-30.0"], ["1077.5", "556.1"], ["-30.0", "556.1"]], "Rules": ["GATE(5,5)", "SD(5,5)", "GATE_SD(0.5)", "GATE_ITO(0.5)", "SD_ITO(0.5)"]}